tensorkiko/__init__.py
tensorkiko/visualize.py
tensorkiko/modules/__init__.py
tensorkiko/modules/ascii_logo.py
tensorkiko/modules/convert_ckpt_st.py
tensorkiko/modules/model_loader.py
tensorkiko/modules/tensor_processing.py
tensorkiko/static/css/styles.css
tensorkiko/static/js/scripts.js
tensorkiko/static/templates/index.html
tensorkiko-0.1.26.dist-info/LICENSE
tensorkiko-0.1.26.dist-info/METADATA
tensorkiko-0.1.26.dist-info/WHEEL
tensorkiko-0.1.26.dist-info/entry_points.txt
tensorkiko-0.1.26.dist-info/top_level.txt
tensorkiko-0.1.26.dist-info/RECORD
